mylib034/__init__.py
mylib034-0.1.dist-info/LICENSE.txt
mylib034-0.1.dist-info/METADATA
mylib034-0.1.dist-info/WHEEL
mylib034-0.1.dist-info/top_level.txt
mylib034-0.1.dist-info/RECORD
